airflow_providers_mattermost/__init__.py
airflow_providers_mattermost/common/__init__.py
airflow_providers_mattermost/common/attachments.py
airflow_providers_mattermost/common/types.py
airflow_providers_mattermost/hooks/__init__.py
airflow_providers_mattermost/hooks/mattermost.py
airflow_providers_mattermost/notifiers/__init__.py
airflow_providers_mattermost/notifiers/mattermost.py
airflow_providers_mattermost/operators/__init__.py
airflow_providers_mattermost/operators/mattermost.py
airflow_providers_mattermost-0.3.0.dist-info/LICENSE
airflow_providers_mattermost-0.3.0.dist-info/METADATA
airflow_providers_mattermost-0.3.0.dist-info/WHEEL
airflow_providers_mattermost-0.3.0.dist-info/entry_points.txt
airflow_providers_mattermost-0.3.0.dist-info/top_level.txt
airflow_providers_mattermost-0.3.0.dist-info/RECORD
