Metadata-Version: 2.1
Name: airflow-providers-mattermost
Version: 0.3.0
Summary: Apache Airflow Mattermost provider
Author-email: mee7ya <bas9339@gmail.com>
License: Apache License
Keywords: apache,airflow,mattermost,provider
Classifier: Development Status :: 4 - Beta
Classifier: Framework :: Apache Airflow
Classifier: Framework :: Apache Airflow :: Provider
Requires-Python: <3.13,>=3.10
License-File: LICENSE
Requires-Dist: apache-airflow >=2.6.0
Requires-Dist: requests >=2.27.0
